medchem/__init__.py
medchem/_version.py
medchem/cli.py
medchem/constraints.py
medchem/catalogs/__init__.py
medchem/catalogs/_catalogs.py
medchem/complexity/__init__.py
medchem/complexity/_calc.py
medchem/complexity/_filter.py
medchem/data/__init__.py
medchem/data/bredt.csv
medchem/data/chemical_groups.csv
medchem/data/common_alerts_collection.csv
medchem/data/grammar.lark
medchem/data/graph.csv
medchem/data/medchem_rule_list.csv
medchem/data/nibr.csv
medchem/data/smarts_bank.csv
medchem/data/charge_assigner/4_amino_pyridine.qry
medchem/data/charge_assigner/N_acylpyrazolidinone.qry
medchem/data/charge_assigner/N_acylsulfonamide.qry
medchem/data/charge_assigner/__init__.py
medchem/data/charge_assigner/acid.qry
medchem/data/charge_assigner/aliphatic_amine_restricted.qry
medchem/data/charge_assigner/amidine.qry
medchem/data/charge_assigner/amino_terminal_restricted.qry
medchem/data/charge_assigner/carboxylic_acid.qry
medchem/data/charge_assigner/guanidine.qry
medchem/data/charge_assigner/imidazole_basic.qry
medchem/data/charge_assigner/negative
medchem/data/charge_assigner/phenolate.qry
medchem/data/charge_assigner/phosphonate.qry
medchem/data/charge_assigner/positive
medchem/data/charge_assigner/pyrazolidinone.qry
medchem/data/charge_assigner/queries
medchem/data/charge_assigner/sulfonic_acid.qry
medchem/data/charge_assigner/tetrazole.qry
medchem/data/charge_assigner/thiazolidinedione.qry
medchem/data/complexity/__init__.py
medchem/data/complexity/zinc_12_stats.csv
medchem/data/complexity/zinc_15_available_stats.csv
medchem/data/queries/3_valent_halogen.qry
medchem/data/queries/3_valent_iodine.qry
medchem/data/queries/4_valent_sulphur_2_connections.qry
medchem/data/queries/6_membered_aromatic_sulfur.qry
medchem/data/queries/8_aminoquinoline.qry
medchem/data/queries/8_hydroxyquinoline.qry
medchem/data/queries/9_aminoacridine.qry
medchem/data/queries/O_alkyl_hydroxylamine.qry
medchem/data/queries/__init__.py
medchem/data/queries/acetal_1_in_ring.qry
medchem-2.0.5.dist-info/LICENSE.md
medchem-2.0.5.dist-info/METADATA
medchem-2.0.5.dist-info/WHEEL
medchem-2.0.5.dist-info/entry_points.txt
medchem-2.0.5.dist-info/top_level.txt
medchem-2.0.5.dist-info/RECORD
