Metadata-Version: 2.1
Name: medchem
Version: 2.0.5
Summary: Medchem: Molecular filtering for drug discovery.
Author-email: Emmanuel Noutahi <emmanuel@valencediscovery.com>, Hadrien Mary <hadrien@valencediscovery.com>
Project-URL: Source Code, https://github.com/datamol-io/medchem
Project-URL: Bug Tracker, https://github.com/datamol-io/medchem/issues
Project-URL: Documentation, https://medchem-docs.datamol.io/
Classifier: Development Status :: 5 - Production/Stable
Classifier: Intended Audience :: Developers
Classifier: Intended Audience :: Healthcare Industry
Classifier: Intended Audience :: Science/Research
Classifier: Topic :: Scientific/Engineering :: Artificial Intelligence
Classifier: Topic :: Scientific/Engineering :: Bio-Informatics
Classifier: Topic :: Scientific/Engineering :: Information Analysis
Classifier: Topic :: Scientific/Engineering :: Medical Science Apps.
Classifier: Natural Language :: English
Classifier: Operating System :: OS Independent
Classifier: Programming Language :: Python
Classifier: Programming Language :: Python :: 3
Classifier: Programming Language :: Python :: 3.9
Classifier: Programming Language :: Python :: 3.10
Classifier: Programming Language :: Python :: 3.11
Requires-Python: >=3.9
License-File: LICENSE.md
Requires-Dist: typer
Requires-Dist: loguru
Requires-Dist: tqdm
Requires-Dist: numpy
Requires-Dist: lark
Requires-Dist: pandas
Requires-Dist: networkx
Requires-Dist: datamol >=0.10
Requires-Dist: rdkit
